odoo/addons/l10n_mx_cfdi/README.rst
odoo/addons/l10n_mx_cfdi/__init__.py
odoo/addons/l10n_mx_cfdi/__manifest__.py
odoo/addons/l10n_mx_cfdi/data/cfdi_publico_en_general.xml
odoo/addons/l10n_mx_cfdi/data/paper_format.xml
odoo/addons/l10n_mx_cfdi/i18n/l10n_mx_cfdi.pot
odoo/addons/l10n_mx_cfdi/models/__init__.py
odoo/addons/l10n_mx_cfdi/models/cfdi_document.py
odoo/addons/l10n_mx_cfdi/models/cfdi_issuer.py
odoo/addons/l10n_mx_cfdi/models/cfdi_series.py
odoo/addons/l10n_mx_cfdi/models/cfdi_service.py
odoo/addons/l10n_mx_cfdi/models/cfdi_service_topup.py
odoo/addons/l10n_mx_cfdi/models/product_template.py
odoo/addons/l10n_mx_cfdi/models/res_company.py
odoo/addons/l10n_mx_cfdi/models/res_partner.py
odoo/addons/l10n_mx_cfdi/readme/CONFIGURE.md
odoo/addons/l10n_mx_cfdi/readme/CONTRIBUTORS.md
odoo/addons/l10n_mx_cfdi/readme/DESCRIPTION.md
odoo/addons/l10n_mx_cfdi/readme/INSTALL.md
odoo/addons/l10n_mx_cfdi/readme/ROADMAP.md
odoo/addons/l10n_mx_cfdi/reports/report_cfdi_blocks.xml
odoo/addons/l10n_mx_cfdi/security/ir.model.access.csv
odoo/addons/l10n_mx_cfdi/security/l10n_mx_cfdi_security.xml
odoo/addons/l10n_mx_cfdi/static/description/icon.png
odoo/addons/l10n_mx_cfdi/static/description/icon.svg
odoo/addons/l10n_mx_cfdi/static/description/index.html
odoo/addons/l10n_mx_cfdi/tests/__init__.py
odoo/addons/l10n_mx_cfdi/tests/test_cfdi_document.py
odoo/addons/l10n_mx_cfdi/tests/test_cfdi_issuer.py
odoo/addons/l10n_mx_cfdi/tests/test_cfdi_series.py
odoo/addons/l10n_mx_cfdi/tests/test_cfdi_service.py
odoo/addons/l10n_mx_cfdi/tests/test_cfdi_service_topup.py
odoo/addons/l10n_mx_cfdi/tests/test_res_company.py
odoo/addons/l10n_mx_cfdi/views/cfdi_document.xml
odoo/addons/l10n_mx_cfdi/views/cfdi_documents_issued.xml
odoo/addons/l10n_mx_cfdi/views/cfdi_issuer.xml
odoo/addons/l10n_mx_cfdi/views/cfdi_menu.xml
odoo/addons/l10n_mx_cfdi/views/cfdi_series.xml
odoo/addons/l10n_mx_cfdi/views/cfdi_service.xml
odoo/addons/l10n_mx_cfdi/views/product_template.xml
odoo_addon_l10n_mx_cfdi-17.0.1.0.1.dist-info/METADATA
odoo_addon_l10n_mx_cfdi-17.0.1.0.1.dist-info/WHEEL
odoo_addon_l10n_mx_cfdi-17.0.1.0.1.dist-info/top_level.txt
odoo_addon_l10n_mx_cfdi-17.0.1.0.1.dist-info/RECORD
