Metadata-Version: 2.1
Name: odoo-addon-l10n_mx_cfdi
Version: 17.0.1.0.1
Requires-Python: >=3.10
Requires-Dist: facturama
Requires-Dist: odoo-addon-l10n_mx_catalogs>=17.0dev,<17.1dev
Requires-Dist: odoo>=17.0a,<17.1dev
Summary: Allow generating CFDI (Comprobante Fiscal Digital por Internet)
Home-page: https://github.com/OCA/l10n-mexico
License: LGPL-3
Author: =?utf-8?q?Alexis_L=C3=B3pez_Zubieta_=3Calexis=2Elopez=40augetec=2Ecom=3E_=28Auge_TEC=29=2C_Odoo_Community_Association_=28OCA=29?=
Author-email: support@odoo-community.org
Classifier: Programming Language :: Python
Classifier: Framework :: Odoo
Classifier: Framework :: Odoo :: 17.0
Classifier: License :: OSI Approved :: GNU Lesser General Public License v3 (LGPLv3)
